[
	{"input":"236P","aliases":["Gun Flame"]},
	{"input":"214P","aliases":["Gun Flame (Feint)"]},
	{"input":"623S","aliases":["Volcanic Viper"]},
	{"input":"623H","aliases":["Volcanic Viper"]},
	{"input":"j.623S","aliases":["Volcanic Viper"]},
	{"input":"j.623H","aliases":["Volcanic Viper"]},
	{"input":"236K","aliases":["Bandit Revolver"]},
	{"input":"236KK","aliases":["Bandit Revolver"]},
	{"input":"j.236K","aliases":["Bandit Revolver"]},
	{"input":"j.236KK","aliases":["Bandit Revolver"]},
	{"input":"214K","aliases":["Bandit Bringer"]},
	{"input":"j.214K","aliases":["Bandit Bringer"]},
	{"input":"623K","aliases":["Wild Throw"]},
	{"input":"214S","aliases":["Night Raid Vortex"]},
	{"input":"41236H","aliases":["Fafnir"]},
	{"input":"632146H","aliases":["Tyrant Rave"]},
	{"input":"214214H","aliases":["Heavy Mob Cemetery"]}	
]