[
  {
    "input": "c.S",
    "aliases": [
      "5S"
    ]
  },
  {
    "input": "2D",
    "aliases": [
      "Sweep"
    ]
  },
  {
    "input": "5[D]",
    "aliases": [
      "5D!"
    ]
  },
  {
    "input": "6D or 4D",
    "aliases": [
      "Throw",
      "6D",
      "4D"
    ]
  },
  {
    "input": "j.6D or j.4D",
    "aliases": [
      "Air Throw",
      "J6D",
      "J4D"
    ]
  },
  {
    "input": "236D",
    "aliases": [
      "Wild Assault",
      "WA"
    ]
  },
  {
    "input": "236[D]",
    "aliases": [
      "Wild Assault Hold",
      "WAH",
      "WA!",
      "236D!"
    ]
  },
  {
    "input": "236P",
    "aliases": [
      "Alpha Blade Horizontal",
      "P Alpha",
      "PA",
      "HAB",
      "ABH"
    ]
  },
  {
    "input": "j.236P",
    "aliases": [
      "Air Alpha Blade Horizontal",
      "Air P Alpha",
      "APA",
      "AHAB",
      "AABH",
      "JHAB",
      "JABH"
    ]
  },
  {
    "input": "236K",
    "aliases": [
      "Alpha Blade Diagonal",
      "K Alpha",
      "KA",
      "DAB",
      "ABD"
    ]
  },
  {
    "input": "j.236K",
    "aliases": [
      "Air Alpha Blade Diagonal",
      "Air K Alpha",
      "AKA",
      "ADAB",
      "AABD",
      "JDAB",
      "JABD"
    ]
  },
  {
    "input": "623S",
    "aliases": [
      "Beta Blade",
      "Beta",
      "DP",
      "BD"
    ]
  },
  {
    "input": "j.623S",
    "aliases": [
      "Air Beta Blade",
      "Air Beta",
      "Air DP",
      "AB",
      "ADP",
      "JDP",
      "JBD"
    ]
  },
  {
    "input": "214H",
    "aliases": [
      "Tightrope",
      "Rope",
      "TR"
    ]
  },
  {
    "input": "236H",
    "aliases": [
      "Gamma Blade",
      "Gamma",
      "Clone",
      "GB"
    ]
  },
  {
    "input": "236S",
    "aliases": [
      "Resshou",
      "Rekka",
      "Rekka 1",
      "Rekka1",
      "Sushi"
    ]
  },
  {
    "input": "236S 236S",
    "aliases": [
      "Rokusai",
      "Rekka 2",
      "Rekka2",
      "Rekka Low",
      "Sukiyaki"
    ]
  },
  {
    "input": "236S 236K",
    "aliases": [
      "Senshuu",
      "Rekka 3",
      "Rekka3",
      "Rekka Overhead",
      "Banzai"
    ]
  },
  {
    "input": "63214S",
    "aliases": [
      "Genrouzan",
      "Command Grab",
      "Leaf Throw",
      "Leaf Grab",
      "CG",
      "624S"
    ]
  },
  {
    "input": "j.214P",
    "aliases": [
      "Shuriken"
    ]
  },
  {
    "input": "236236P",
    "aliases": [
      "Banki Messai",
      "Super",
      "Clone Super",
      "BM",
      "CUS"
    ]
  },
  {
    "input": "632146H",
    "aliases": [
      "Zansei Rouga",
      "Teleport Super",
      "ZR",
      "TP"
    ]
  },
  {
    "input": "j.632146H",
    "aliases": [
      "Air Zansei Rouga",
      "Air Super",
      "Air Teleport Super",
      "JZR",
      "AZR",
      "AS",
      "JUS",
      "ATS",
      "JTP"
    ]
  }
]
